pyACS/__init__.py
pyACS/__main__.py
pyACS/acs.py
pyACS/dev.py
pyACS/test.py
pyACS-0.1.1.dist-info/LICENSE
pyACS-0.1.1.dist-info/METADATA
pyACS-0.1.1.dist-info/WHEEL
pyACS-0.1.1.dist-info/top_level.txt
pyACS-0.1.1.dist-info/RECORD
