Metadata-Version: 2.1
Name: pyACS
Version: 0.1.1
Summary: Unpack and calibrate binary data from a WetLabs ACS
Home-page: https://github.com/OceanOptics/pyACS/
Author: Nils Haentjens
Author-email: nils.haentjens@maine.edu
License: MIT
Classifier: Programming Language :: Python :: 3
Classifier: License :: OSI Approved :: MIT License
Classifier: Operating System :: OS Independent
Classifier: Development Status :: 3 - Alpha
Classifier: Intended Audience :: Education
Classifier: Intended Audience :: Science/Research
License-File: LICENSE
Requires-Dist: numpy
